{"metadata": {"dbt_schema_version": "https://schemas.getdbt.com/dbt/run-results/v4.json", "dbt_version": "1.2.2", "generated_at": "2022-10-16T10:18:16.139759Z", "invocation_id": "2d21ea6d-92b3-46af-9795-9161916064d3", "env": {}}, "results": [{"status": "success", "timing": [{"name": "compile", "started_at": "2022-10-16T10:18:16.024841Z", "completed_at": "2022-10-16T10:18:16.028727Z"}, {"name": "execute", "started_at": "2022-10-16T10:18:16.029440Z", "completed_at": "2022-10-16T10:18:16.029468Z"}], "thread_id": "Thread-1", "execution_time": 0.0060329437255859375, "adapter_response": {}, "message": null, "failures": null, "unique_id": "model.carbon_emissions_transform.dashboard_carbon_monitoring"}, {"status": "success", "timing": [{"name": "compile", "started_at": "2022-10-16T10:18:16.032419Z", "completed_at": "2022-10-16T10:18:16.049293Z"}, {"name": "execute", "started_at": "2022-10-16T10:18:16.049985Z", "completed_at": "2022-10-16T10:18:16.049997Z"}], "thread_id": "Thread-1", "execution_time": 0.018895864486694336, "adapter_response": {}, "message": null, "failures": null, "unique_id": "test.carbon_emissions_transform.not_null_dashboard_carbon_monitoring_avg_pod_energy.6ce6177d4b"}, {"status": "success", "timing": [{"name": "compile", "started_at": "2022-10-16T10:18:16.052312Z", "completed_at": "2022-10-16T10:18:16.057847Z"}, {"name": "execute", "started_at": "2022-10-16T10:18:16.058528Z", "completed_at": "2022-10-16T10:18:16.058540Z"}], "thread_id": "Thread-1", "execution_time": 0.007572174072265625, "adapter_response": {}, "message": null, "failures": null, "unique_id": "test.carbon_emissions_transform.not_null_dashboard_carbon_monitoring_avg_pod_energy_kwh.9ca1bbff68"}, {"status": "success", "timing": [{"name": "compile", "started_at": "2022-10-16T10:18:16.060848Z", "completed_at": "2022-10-16T10:18:16.067818Z"}, {"name": "execute", "started_at": "2022-10-16T10:18:16.068505Z", "completed_at": "2022-10-16T10:18:16.068517Z"}], "thread_id": "Thread-1", "execution_time": 0.009005308151245117, "adapter_response": {}, "message": null, "failures": null, "unique_id": "test.carbon_emissions_transform.not_null_dashboard_carbon_monitoring_carbon_intensity.5be725f405"}, {"status": "success", "timing": [{"name": "compile", "started_at": "2022-10-16T10:18:16.070797Z", "completed_at": "2022-10-16T10:18:16.076375Z"}, {"name": "execute", "started_at": "2022-10-16T10:18:16.077060Z", "completed_at": "2022-10-16T10:18:16.077071Z"}], "thread_id": "Thread-1", "execution_time": 0.0075836181640625, "adapter_response": {}, "message": null, "failures": null, "unique_id": "test.carbon_emissions_transform.not_null_dashboard_carbon_monitoring_day.52827ffb45"}, {"status": "success", "timing": [{"name": "compile", "started_at": "2022-10-16T10:18:16.079363Z", "completed_at": "2022-10-16T10:18:16.085001Z"}, {"name": "execute", "started_at": "2022-10-16T10:18:16.085648Z", "completed_at": "2022-10-16T10:18:16.085659Z"}], "thread_id": "Thread-1", "execution_time": 0.007636070251464844, "adapter_response": {}, "message": null, "failures": null, "unique_id": "test.carbon_emissions_transform.not_null_dashboard_carbon_monitoring_gCO2eq.e5bca16acc"}, {"status": "success", "timing": [{"name": "compile", "started_at": "2022-10-16T10:18:16.087999Z", "completed_at": "2022-10-16T10:18:16.093681Z"}, {"name": "execute", "started_at": "2022-10-16T10:18:16.094367Z", "completed_at": "2022-10-16T10:18:16.094379Z"}], "thread_id": "Thread-1", "execution_time": 0.0077364444732666016, "adapter_response": {}, "message": null, "failures": null, "unique_id": "test.carbon_emissions_transform.not_null_dashboard_carbon_monitoring_hour.1cb6b5ee5b"}, {"status": "success", "timing": [{"name": "compile", "started_at": "2022-10-16T10:18:16.096691Z", "completed_at": "2022-10-16T10:18:16.102229Z"}, {"name": "execute", "started_at": "2022-10-16T10:18:16.102905Z", "completed_at": "2022-10-16T10:18:16.102916Z"}], "thread_id": "Thread-1", "execution_time": 0.00763702392578125, "adapter_response": {}, "message": null, "failures": null, "unique_id": "test.carbon_emissions_transform.not_null_dashboard_carbon_monitoring_month.8161b6b9af"}, {"status": "success", "timing": [{"name": "compile", "started_at": "2022-10-16T10:18:16.105259Z", "completed_at": "2022-10-16T10:18:16.110888Z"}, {"name": "execute", "started_at": "2022-10-16T10:18:16.111537Z", "completed_at": "2022-10-16T10:18:16.111548Z"}], "thread_id": "Thread-1", "execution_time": 0.0077362060546875, "adapter_response": {}, "message": null, "failures": null, "unique_id": "test.carbon_emissions_transform.not_null_dashboard_carbon_monitoring_pod_name.290f43c819"}, {"status": "success", "timing": [{"name": "compile", "started_at": "2022-10-16T10:18:16.113827Z", "completed_at": "2022-10-16T10:18:16.119328Z"}, {"name": "execute", "started_at": "2022-10-16T10:18:16.120011Z", "completed_at": "2022-10-16T10:18:16.120022Z"}], "thread_id": "Thread-1", "execution_time": 0.0074977874755859375, "adapter_response": {}, "message": null, "failures": null, "unique_id": "test.carbon_emissions_transform.not_null_dashboard_carbon_monitoring_pod_namespace.77f866ca5f"}, {"status": "success", "timing": [{"name": "compile", "started_at": "2022-10-16T10:18:16.122287Z", "completed_at": "2022-10-16T10:18:16.128010Z"}, {"name": "execute", "started_at": "2022-10-16T10:18:16.128697Z", "completed_at": "2022-10-16T10:18:16.128708Z"}], "thread_id": "Thread-1", "execution_time": 0.0077555179595947266, "adapter_response": {}, "message": null, "failures": null, "unique_id": "test.carbon_emissions_transform.not_null_dashboard_carbon_monitoring_region.b2bf28d0f3"}, {"status": "success", "timing": [{"name": "compile", "started_at": "2022-10-16T10:18:16.130998Z", "completed_at": "2022-10-16T10:18:16.136544Z"}, {"name": "execute", "started_at": "2022-10-16T10:18:16.137221Z", "completed_at": "2022-10-16T10:18:16.137233Z"}], "thread_id": "Thread-1", "execution_time": 0.007585048675537109, "adapter_response": {}, "message": null, "failures": null, "unique_id": "test.carbon_emissions_transform.not_null_dashboard_carbon_monitoring_unit_value.d75bdc78d0"}], "elapsed_time": 0.2848777770996094, "args": {"write_json": true, "use_colors": true, "printer_width": 80, "version_check": true, "partial_parse": true, "static_parser": true, "profiles_dir": "/opt/app-root/src", "send_anonymous_usage_stats": true, "event_buffer_size": 100000, "quiet": false, "no_print": false, "compile": true, "which": "generate", "rpc_method": "docs.generate", "indirect_selection": "eager"}}